Flask_Restler-1.19.5.dist-info/DESCRIPTION.rst
Flask_Restler-1.19.5.dist-info/METADATA
Flask_Restler-1.19.5.dist-info/RECORD
Flask_Restler-1.19.5.dist-info/WHEEL
Flask_Restler-1.19.5.dist-info/metadata.json
Flask_Restler-1.19.5.dist-info/top_level.txt
flask_restler/__init__.py
flask_restler/api.py
flask_restler/auth.py
flask_restler/fields.py
flask_restler/filters.py
flask_restler/mongo.py
flask_restler/peewee.py
flask_restler/resource.py
flask_restler/runner.py
flask_restler/sqlalchemy.py
flask_restler/templates/swagger.html
