Metadata-Version: 2.0
Name: Flask-Restler
Version: 1.19.5
Summary: Build REST API for Flask using Marshmallow.
Home-page: https://github.com/klen/flask-restler
Author: Kirill Klenov
Author-email: horneds@gmail.com
License: MIT
Keywords: flask,marshmallow,rest,api
Platform: Any
Classifier: Development Status :: 4 - Beta
Classifier: Intended Audience :: Developers
Classifier: License :: OSI Approved :: BSD License
Classifier: Natural Language :: English
Classifier: Natural Language :: Russian
Classifier: Operating System :: OS Independent
Classifier: Programming Language :: Python :: 2
Classifier: Programming Language :: Python :: 3
Classifier: Programming Language :: Python
Classifier: Topic :: Software Development :: Libraries :: Python Modules
Classifier: Topic :: Software Development :: Testing
Classifier: Topic :: Utilities
Requires-Dist: Flask (>=0.11.1)
Requires-Dist: apispec (>=0.39.0)
Requires-Dist: cached-property (>=1.4.3)
